flake8_maya_flags.py
flake8_maya_flags-1.1.0.dist-info/LICENSE
flake8_maya_flags-1.1.0.dist-info/METADATA
flake8_maya_flags-1.1.0.dist-info/WHEEL
flake8_maya_flags-1.1.0.dist-info/entry_points.txt
flake8_maya_flags-1.1.0.dist-info/top_level.txt
flake8_maya_flags-1.1.0.dist-info/RECORD
